{
  "dashboard": {
    "title": "Dashboard de Base de Datos",
    "tags": ["mysql", "base-datos"],
    "timezone": "browser",
    "uid": "base-datos-dashboard",
    "version": 1,
    "schemaVersion": 38,
    "refresh": "10s",
    "panels": [
      {
        "id": 1,
        "title": "Conexiones MySQL",
        "type": "timeseries",
        "gridPos": {"h": 8, "w": 12, "x": 0, "y": 0},
        "targets": [
          {
            "expr": "mysql_global_status_threads_connected",
            "legendFormat": "Conexiones Activas",
            "refId": "A",
            "datasource": {
              "type": "prometheus",
              "uid": "prometheus"
            }
          },
          {
            "expr": "mysql_global_variables_max_connections",
            "legendFormat": "Máximo de Conexiones",
            "refId": "B",
            "datasource": {
              "type": "prometheus",
              "uid": "prometheus"
            }
          }
        ],
        "fieldConfig": {
          "defaults": {
            "color": {
              "mode": "palette-classic"
            },
            "custom": {
              "axisLabel": "",
              "axisPlacement": "auto",
              "barAlignment": 0,
              "drawStyle": "line",
              "fillOpacity": 10,
              "gradientMode": "none",
              "hideFrom": {
                "tooltip": false,
                "viz": false,
                "legend": false
              },
              "lineInterpolation": "linear",
              "lineWidth": 1,
              "pointSize": 5,
              "scaleDistribution": {
                "type": "linear"
              },
              "showPoints": "never",
              "spanNulls": false
            },
            "mappings": [],
            "thresholds": {
              "mode": "absolute",
              "steps": [
                {
                  "color": "green",
                  "value": null
                }
              ]
            },
            "unit": "short"
          },
          "overrides": []
        },
        "options": {
          "tooltip": {
            "mode": "multi"
          },
          "legend": {
            "calcs": [],
            "displayMode": "list",
            "placement": "bottom"
          }
        }
      },
      {
        "id": 2,
        "title": "Consultas por Segundo",
        "type": "timeseries",
        "gridPos": {"h": 8, "w": 12, "x": 12, "y": 0},
        "targets": [
          {
            "expr": "rate(mysql_global_status_questions[5m])",
            "legendFormat": "Consultas/seg",
            "refId": "A",
            "datasource": {
              "type": "prometheus",
              "uid": "prometheus"
            }
          }
        ],
        "fieldConfig": {
          "defaults": {
            "color": {
              "mode": "palette-classic"
            },
            "custom": {
              "axisLabel": "",
              "axisPlacement": "auto",
              "barAlignment": 0,
              "drawStyle": "line",
              "fillOpacity": 10,
              "gradientMode": "none",
              "hideFrom": {
                "tooltip": false,
                "viz": false,
                "legend": false
              },
              "lineInterpolation": "linear",
              "lineWidth": 1,
              "pointSize": 5,
              "scaleDistribution": {
                "type": "linear"
              },
              "showPoints": "never",
              "spanNulls": false
            },
            "mappings": [],
            "thresholds": {
              "mode": "absolute",
              "steps": [
                {
                  "color": "green",
                  "value": null
                }
              ]
            },
            "unit": "ops"
          },
          "overrides": []
        },
        "options": {
          "tooltip": {
            "mode": "multi"
          },
          "legend": {
            "calcs": [],
            "displayMode": "list",
            "placement": "bottom"
          }
        }
      },
      {
        "id": 3,
        "title": "Operaciones de Lectura/Escritura",
        "type": "timeseries",
        "gridPos": {"h": 8, "w": 12, "x": 0, "y": 8},
        "targets": [
          {
            "expr": "rate(mysql_global_status_com_select[5m])",
            "legendFormat": "SELECT",
            "refId": "A",
            "datasource": {
              "type": "prometheus",
              "uid": "prometheus"
            }
          },
          {
            "expr": "rate(mysql_global_status_com_insert[5m])",
            "legendFormat": "INSERT",
            "refId": "B",
            "datasource": {
              "type": "prometheus",
              "uid": "prometheus"
            }
          },
          {
            "expr": "rate(mysql_global_status_com_update[5m])",
            "legendFormat": "UPDATE",
            "refId": "C",
            "datasource": {
              "type": "prometheus",
              "uid": "prometheus"
            }
          },
          {
            "expr": "rate(mysql_global_status_com_delete[5m])",
            "legendFormat": "DELETE",
            "refId": "D",
            "datasource": {
              "type": "prometheus",
              "uid": "prometheus"
            }
          }
        ],
        "fieldConfig": {
          "defaults": {
            "color": {
              "mode": "palette-classic"
            },
            "custom": {
              "axisLabel": "",
              "axisPlacement": "auto",
              "barAlignment": 0,
              "drawStyle": "line",
              "fillOpacity": 10,
              "gradientMode": "none",
              "hideFrom": {
                "tooltip": false,
                "viz": false,
                "legend": false
              },
              "lineInterpolation": "linear",
              "lineWidth": 1,
              "pointSize": 5,
              "scaleDistribution": {
                "type": "linear"
              },
              "showPoints": "never",
              "spanNulls": false
            },
            "mappings": [],
            "thresholds": {
              "mode": "absolute",
              "steps": [
                {
                  "color": "green",
                  "value": null
                }
              ]
            },
            "unit": "ops"
          },
          "overrides": []
        },
        "options": {
          "tooltip": {
            "mode": "multi"
          },
          "legend": {
            "calcs": [],
            "displayMode": "list",
            "placement": "bottom"
          }
        }
      },
      {
        "id": 4,
        "title": "Tamaño de Base de Datos",
        "type": "stat",
        "gridPos": {"h": 4, "w": 6, "x": 12, "y": 8},
        "targets": [
          {
            "expr": "mysql_info_schema_size_bytes",
            "legendFormat": "Tamaño BD",
            "refId": "A",
            "datasource": {
              "type": "prometheus",
              "uid": "prometheus"
            }
          }
        ],
        "fieldConfig": {
          "defaults": {
            "color": {
              "mode": "thresholds"
            },
            "mappings": [],
            "thresholds": {
              "mode": "absolute",
              "steps": [
                {
                  "color": "green",
                  "value": null
                }
              ]
            },
            "unit": "bytes"
          },
          "overrides": []
        },
        "options": {
          "colorMode": "value",
          "graphMode": "area",
          "justifyMode": "auto",
          "orientation": "auto",
          "reduceOptions": {
            "values": false,
            "calcs": [
              "lastNotNull"
            ],
            "fields": ""
          },
          "textMode": "auto"
        }
      },
      {
        "id": 5,
        "title": "Uptime MySQL",
        "type": "stat",
        "gridPos": {"h": 4, "w": 6, "x": 18, "y": 8},
        "targets": [
          {
            "expr": "mysql_global_status_uptime",
            "legendFormat": "Uptime (seg)",
            "refId": "A",
            "datasource": {
              "type": "prometheus",
              "uid": "prometheus"
            }
          }
        ],
        "fieldConfig": {
          "defaults": {
            "color": {
              "mode": "thresholds"
            },
            "mappings": [],
            "thresholds": {
              "mode": "absolute",
              "steps": [
                {
                  "color": "green",
                  "value": null
                }
              ]
            },
            "unit": "s"
          },
          "overrides": []
        },
        "options": {
          "colorMode": "value",
          "graphMode": "area",
          "justifyMode": "auto",
          "orientation": "auto",
          "reduceOptions": {
            "values": false,
            "calcs": [
              "lastNotNull"
            ],
            "fields": ""
          },
          "textMode": "auto"
        }
      }
    ]
  }
}
